online_behavioral_modeling/__init__.py
online_behavioral_modeling-1.0.0.dist-info/METADATA
online_behavioral_modeling-1.0.0.dist-info/WHEEL
online_behavioral_modeling-1.0.0.dist-info/RECORD
