Metadata-Version: 2.4
Name: online-behavioral-modeling
Version: 1.0.0
Summary: Tools for online behavioral modeling
Author: Noor Jamaludeen
License: Proprietary
Requires-Python: >=3.9
